Metadata-Version: 2.1
Name: wcs-python3-sdk
Version: 5.0.36
Summary: Wangsu Cloud Storage Command Tool
Home-page: https://wcs.chinanetcenter.com/document/SDK
Author: ChinaNetCenter.Wangsu Cloud Strage
Author-email: cdn_team_storage_wcs@chinanetcenter.com
Maintainer: https://github.com/Wangsu-Cloud-Storage
License: MIT
Platform: UNKNOWN
Classifier: Intended Audience :: Developers
Classifier: Operating System :: OS Independent
Classifier: Programming Language :: Python
Classifier: Programming Language :: Python :: 3
Classifier: Programming Language :: Python :: 3.3
Classifier: Programming Language :: Python :: 3.4
Classifier: Programming Language :: Python :: 3.5
Classifier: Programming Language :: Python :: 3.6
Classifier: Topic :: Internet :: WWW/HTTP :: Dynamic Content
Classifier: Topic :: Software Development :: Libraries :: Python Modules
Requires-Dist: requests (>=2.19.1)
Requires-Dist: argparse
Requires-Dist: lockfile
Requires-Dist: requests-toolbelt
Requires-Dist: pyyaml
Requires-Dist: crcmod (>=1.7)
